core_memory.py
memory_service.py
core_memory_mcp-0.1.6.dist-info/licenses/LICENSE
core_memory_mcp-0.1.6.dist-info/METADATA
core_memory_mcp-0.1.6.dist-info/WHEEL
core_memory_mcp-0.1.6.dist-info/entry_points.txt
core_memory_mcp-0.1.6.dist-info/top_level.txt
core_memory_mcp-0.1.6.dist-info/RECORD
