Metadata-Version: 2.4
Name: core-memory-mcp
Version: 0.1.6
Summary: A local, MCP-compliant, long-term memory service for AI agents.
Author-email: Michael Feng <michael@example.com>
License: GNU GENERAL PUBLIC LICENSE
Project-URL: Homepage, https://github.com/michaelfeng/CoreMemory-MCP
Project-URL: Bug Tracker, https://github.com/michaelfeng/CoreMemory-MCP/issues
Classifier: Programming Language :: Python :: 3
Classifier: Operating System :: OS Independent
Requires-Python: >=3.8
License-File: LICENSE
Requires-Dist: fastapi
Requires-Dist: uvicorn[standard]
Dynamic: license-file
